wordfreak/__init__.py
wordfreak/parser/DocxParser.py
wordfreak/parser/Parser.py
wordfreak/parser/PdfParser.py
wordfreak/parser/TxtParser.py
wordfreak/parser/__init__.py
wordfreak/service/__init__.py
wordfreak/service/wordFrequency.py
wordfreak/util/__init__.py
wordfreak/util/constants.py
wordfreak-0.0.12.dist-info/LICENSE
wordfreak-0.0.12.dist-info/METADATA
wordfreak-0.0.12.dist-info/WHEEL
wordfreak-0.0.12.dist-info/top_level.txt
wordfreak-0.0.12.dist-info/RECORD
