Metadata-Version: 2.1
Name: wordfreak
Version: 0.0.12
Summary: Word Freak is a Python library that extracts word frequencies from files.
Author: Joey Greco
Author-email: joeyagreco@gmail.com
License: MIT License        
License-File: LICENSE
Requires-Dist: PyPDF2
Requires-Dist: docx2txt
Requires-Dist: setuptools
